TagTree/Document.py
TagTree/__init__.py
TagTree/template/Component.py
TagTree/template/Tag.py
TagTree/template/__init__.py
TagTree-1.0.22.dist-info/LICENSE
TagTree-1.0.22.dist-info/METADATA
TagTree-1.0.22.dist-info/WHEEL
TagTree-1.0.22.dist-info/entry_points.txt
TagTree-1.0.22.dist-info/top_level.txt
TagTree-1.0.22.dist-info/RECORD
