Metadata-Version: 2.1
Name: TagTree
Version: 1.0.22
Summary: A Tag Dom Generator module
Home-page: https://github.com/Strovsk/pytagtree
Author: Thiago S C Pereira
Author-email: strovsk@outlook.com
Project-URL: Bug Reports, https://github.com/Strovsk/pytagtree/issues
Project-URL: Funding, https://donate.pypi.org
Project-URL: Say Thanks!, http://saythanks.io/to/example
Project-URL: Source, https://github.com/Strovsk/pytagtree
Keywords: tag,tree,dom,generator,html,markup,xml,tags,xhtml,xcell,drawio
Classifier: Development Status :: 3 - Alpha
Classifier: Intended Audience :: Developers
Classifier: Topic :: Software Development :: Build Tools
Classifier: License :: OSI Approved :: MIT License
Classifier: Programming Language :: Python :: 3
Classifier: Programming Language :: Python :: 3.7
Classifier: Programming Language :: Python :: 3.8
Classifier: Programming Language :: Python :: 3.9
Classifier: Programming Language :: Python :: 3.10
Classifier: Programming Language :: Python :: 3 :: Only
Requires-Python: >=3.7, <4
License-File: LICENSE
Requires-Dist: peppercorn
